sussy/__init__.py
sussy/prompts.py
sussypy-0.1.0.dev0.dist-info/LICENCE
sussypy-0.1.0.dev0.dist-info/METADATA
sussypy-0.1.0.dev0.dist-info/WHEEL
sussypy-0.1.0.dev0.dist-info/top_level.txt
sussypy-0.1.0.dev0.dist-info/RECORD
